[
    {
        "key": "dbln",
        "value": "%7B%22100084487161562%22%3A%22xUtFuRKX%22%2C%2261553762854097%22%3A%22ZddHLnHR%22%2C%22100085062292282%22%3A%22Z21KAazI%22%7D",
        "domain": "facebook.com",
        "path": "/login/device-based/",
        "hostOnly": false,
        "creation": "2024-12-07T14:46:21.107Z",
        "lastAccessed": "2024-12-07T14:46:21.108Z"
    },
    {
        "key": "datr",
        "value": "2tNTZwtpqNGEVn0GKGVAzq8u",
        "domain": "facebook.com",
        "path": "/",
        "hostOnly": false,
        "creation": "2024-12-07T14:46:21.108Z",
        "lastAccessed": "2024-12-07T14:46:21.109Z"
    },
    {
        "key": "sb",
        "value": "2tNTZ_oCXTz5DkZCNx-bkmkO",
        "domain": "facebook.com",
        "path": "/",
        "hostOnly": false,
        "creation": "2024-12-07T14:46:21.109Z",
        "lastAccessed": "2024-12-07T14:46:21.109Z"
    },
    {
        "key": "vpd",
        "value": "v1%3B774x384x1.875",
        "domain": "facebook.com",
        "path": "/",
        "hostOnly": false,
        "creation": "2024-12-07T14:46:21.109Z",
        "lastAccessed": "2024-12-07T14:46:21.109Z"
    },
    {
        "key": "ps_l",
        "value": "1",
        "domain": "facebook.com",
        "path": "/",
        "hostOnly": false,
        "creation": "2024-12-07T14:46:21.109Z",
        "lastAccessed": "2024-12-07T14:46:21.109Z"
    },
    {
        "key": "ps_n",
        "value": "1",
        "domain": "facebook.com",
        "path": "/",
        "hostOnly": false,
        "creation": "2024-12-07T14:46:21.109Z",
        "lastAccessed": "2024-12-07T14:46:21.109Z"
    },
    {
        "key": "locale",
        "value": "bn_IN",
        "domain": "facebook.com",
        "path": "/",
        "hostOnly": false,
        "creation": "2024-12-07T14:46:21.109Z",
        "lastAccessed": "2024-12-07T14:46:21.109Z"
    },
    {
        "key": "wd",
        "value": "384x774",
        "domain": "facebook.com",
        "path": "/",
        "hostOnly": false,
        "creation": "2024-12-07T14:46:21.109Z",
        "lastAccessed": "2024-12-07T14:46:21.109Z"
    },
    {
        "key": "c_user",
        "value": "100085062292282",
        "domain": "facebook.com",
        "path": "/",
        "hostOnly": false,
        "creation": "2024-12-07T14:46:21.109Z",
        "lastAccessed": "2024-12-07T14:46:21.109Z"
    },
    {
        "key": "fr",
        "value": "02pAvs9lw3zw2mrex.AWWQ7kuQkPisSidAiHfsW7_2Q2c.BnU9Pa..AAA.0.0.BnVDt9.AWXRKsIGyUk",
        "domain": "facebook.com",
        "path": "/",
        "hostOnly": false,
        "creation": "2024-12-07T14:46:21.109Z",
        "lastAccessed": "2024-12-07T14:46:21.109Z"
    },
    {
        "key": "xs",
        "value": "33%3AfQDyNtxd0h7KMw%3A2%3A1733573505%3A-1%3A5223",
        "domain": "facebook.com",
        "path": "/",
        "hostOnly": false,
        "creation": "2024-12-07T14:46:21.109Z",
        "lastAccessed": "2024-12-07T14:46:21.109Z"
    },
    {
        "key": "fbl_st",
        "value": "101032238%3BT%3A28893046",
        "domain": "facebook.com",
        "path": "/",
        "hostOnly": false,
        "creation": "2024-12-07T14:46:21.109Z",
        "lastAccessed": "2024-12-07T14:46:21.109Z"
    },
    {
        "key": "wl_cbv",
        "value": "v2%3Bclient_version%3A2690%3Btimestamp%3A1733582761%3BCRCM%3A-1437660626",
        "domain": "facebook.com",
        "path": "/",
        "hostOnly": false,
        "creation": "2024-12-07T14:46:21.109Z",
        "lastAccessed": "2024-12-07T14:46:21.109Z"
    }
]
